proto_dist_ml/mglvq.py
proto_dist_ml/rglvq.py
proto_dist_ml/rng.py
proto_dist_ml-1.0.1.dist-info/LICENSE.md
proto_dist_ml-1.0.1.dist-info/METADATA
proto_dist_ml-1.0.1.dist-info/WHEEL
proto_dist_ml-1.0.1.dist-info/top_level.txt
proto_dist_ml-1.0.1.dist-info/RECORD
