Metadata-Version: 2.1
Name: proto-dist-ml
Version: 1.0.1
Summary: Prototype-based Machine Learning on Distance Data.
Home-page: https://gitlab.ub.uni-bielefeld.de/bpaassen/proto-dist-ml
Author: Benjamin Paassen
Author-email: bpaassen@techfak.uni-bielefeld.de
License: UNKNOWN
Keywords: relational-neural-gas learning-vector-quantization lvq clustering classification machine-learning distances
Platform: UNKNOWN
Classifier: Programming Language :: Python :: 3
Classifier: License :: OSI Approved :: GNU General Public License v3 (GPLv3)
Classifier: Operating System :: OS Independent
Requires-Dist: numpy
Requires-Dist: scikit-learn
Requires-Dist: scipy
